{
    "post_title": "Учні 6-А класу на уроці технологій презентували свої новорічні вироби",
    "post_date": "22.12.2023",
    "post_text": [
        "\n\n\n<h3>Учні презентували свої новорічні вироби.</h3><h3>Атмосфера в класі одразу стала святковою.</h3><p><span class=\"img_text_tpl img_text_no s330\"><span class=\"overlay_tpl\"></span></span> <span class=\"img_text_tpl img_text_no s330\"><span class=\"overlay_tpl\"></span></span> </p><p><span class=\"img_text_tpl img_text_no s600\"><span class=\"overlay_tpl\"></span></span> </p> "
    ],
    "post_documents": [],
    "post_videos": [],
    "main_image": "main_image.jpg",
    "post_images": [
        "post_image_1.jpg",
        "post_image_2.jpg"
    ]
}