{
    "post_title": "Тему \"Про що розповідають карти\" з ЯДС діти 4-Б класу завершили проєктом \"Пізнаємо Україну\", виконавши макет мапи України.",
    "post_date": "13.09.2021",
    "post_text": [
        "\n\n\n<p>Тему \"Про що розповідають карти\" з ЯДС діти 4-Б класу (вчитель Антонюк Т.О.) завершили проєктом \"Пізнаємо Україну\", виконавши макет мапи України. Робота виконувалось із задоволенням, цікаво, змістовно й творчо.</p><p><span class=\"img_text_tpl img_text_no s600\"><span class=\"overlay_tpl\"></span></span> </p><p class=\"clearfloat wym_center\"> </p> "
    ],
    "post_documents": [],
    "post_videos": [],
    "main_image": "main_image.jpg",
    "post_images": []
}