{
    "post_title": "«Найдорожче. Мир в дитячих долонях»",
    "post_date": "12.11.2015",
    "post_text": [
        "\n\n\n<p class=\"wym_center\"> <span class=\"img_text_tpl img_text_no s330\"><span class=\"overlay_tpl\"></span></span> </p><p>11 листопада 2015 року в затишній залі СЗШ № 201 відбувся фінальний галаконцерт та нагородження переможців XVI районного конкурсу патріотичноїпісні «Найдорожче. Мир в дитячих долонях». Учениця 7-А класу СЗШ №201 Чернишева Юлія зайняла почесне 1- місце в середній віковій групі.Вітаємо юну артистку з перемогою!</p><hr/><p class=\"wym_center\"> <span class=\"img_text_tpl img_text_no s140\"><span class=\"overlay_tpl\"></span></span> <span class=\"img_text_tpl img_text_no s330\"><span class=\"overlay_tpl\"></span></span> </p> "
    ],
    "post_documents": [],
    "post_videos": [],
    "main_image": "main_image.JPG",
    "post_images": [
        "post_image_1.jpg",
        "post_image_2.jpg"
    ]
}