{
    "post_title": "У 4-Б класі відбувся відкритий урок з літературного читання",
    "post_date": "17.02.2023",
    "post_text": [
        "\n\n\n<h3>Урок розпочався інсценізацією казки \"Біда навчить\", в якій кожен учень мав свою роль. А після казки здобувачі освіти обговорили головну думку твору та зробили виставку ілюстрацій до творів.</h3><h3> Діти підготували цікаві факти із життя та творчості Лесі Українки. Четвертокласники вправно працювали з мнемотаблицями, виконували завдання в групах, використовували ключові компетентності, такі як: читали з розумінням, висловлювали власні думки, виконували творчі завдання, вільно володіли державною мовою.</h3><h3> Наталія Вікторівна використовувала міжпредметні зв'язки, вдало підібрала дидактичні ігри, активізувала візуальну пам'ять за допомогою наочності.</h3><p><span class=\"img_text_tpl img_text_no s600\"><span class=\"overlay_tpl\"></span></span> </p> "
    ],
    "post_documents": [],
    "post_videos": [],
    "main_image": "main_image.jpg",
    "post_images": []
}